LICENSE
README.md
pyproject.toml
src/python_requests.egg-info/PKG-INFO
src/python_requests.egg-info/SOURCES.txt
src/python_requests.egg-info/dependency_links.txt
src/python_requests.egg-info/top_level.txt
src/requests/__init__.py