Metadata-Version: 2.1
Name: python-requests
Version: 0.0.0.2
Summary: This is a sham PyPI package creation. In fact, it is a could-be / would-be malicious code injection
Author-email: Kale Franz <eetygr@gmail.com>
Project-URL: Homepage, https://github.com/kalefranz/python-requests
Classifier: Programming Language :: Python :: 3
Classifier: License :: OSI Approved :: MIT License
Classifier: Operating System :: OS Independent
Requires-Python: >=3.7
License-File: LICENSE
